{
  "version": "5",
  "dialect": "mysql",
  "id": "0432ef8e-a47a-4621-ac46-26f086adcf68",
  "prevId": "4fbdeb8a-13cf-440f-bb23-3e25396f2c3e",
  "tables": {
    "documents": {
      "name": "documents",
      "columns": {
        "id": {
          "name": "id",
          "type": "bigint",
          "primaryKey": false,
          "notNull": true,
          "autoincrement": true
        },
        "slug": {
          "name": "slug",
          "type": "varchar(255)",
          "primaryKey": false,
          "notNull": true,
          "autoincrement": false
        },
        "locale": {
          "name": "locale",
          "type": "varchar(16)",
          "primaryKey": false,
          "notNull": true,
          "autoincrement": false
        },
        "title": {
          "name": "title",
          "type": "varchar(255)",
          "primaryKey": false,
          "notNull": true,
          "autoincrement": false
        },
        "description": {
          "name": "description",
          "type": "text",
          "primaryKey": false,
          "notNull": true,
          "autoincrement": false
        },
        "content": {
          "name": "content",
          "type": "text",
          "primaryKey": false,
          "notNull": true,
          "autoincrement": false
        },
        "source_path": {
          "name": "source_path",
          "type": "varchar(1024)",
          "primaryKey": false,
          "notNull": true,
          "autoincrement": false
        },
        "embedding": {
          "name": "embedding",
          "type": "vector(1024)",
          "primaryKey": false,
          "notNull": true,
          "autoincrement": false,
          "generated": {
            "as": "EMBED_TEXT(\"tidbcloud_free/amazon/titan-embed-text-v2\", content)",
            "type": "stored"
          }
        },
        "created_at": {
          "name": "created_at",
          "type": "timestamp",
          "primaryKey": false,
          "notNull": true,
          "autoincrement": false,
          "default": "(now())"
        }
      },
      "indexes": {
        "uniq_slug_locale": {
          "name": "uniq_slug_locale",
          "columns": ["slug", "locale"],
          "isUnique": true
        },
        "idx_title": {
          "name": "idx_title",
          "columns": ["title"],
          "isUnique": false
        }
      },
      "foreignKeys": {},
      "compositePrimaryKeys": {
        "documents_id": {
          "name": "documents_id",
          "columns": ["id"]
        }
      },
      "uniqueConstraints": {},
      "checkConstraint": {}
    },
    "seed_sync_state": {
      "name": "seed_sync_state",
      "columns": {
        "scope": {
          "name": "scope",
          "type": "varchar(64)",
          "primaryKey": false,
          "notNull": true,
          "autoincrement": false
        },
        "source_commit": {
          "name": "source_commit",
          "type": "varchar(64)",
          "primaryKey": false,
          "notNull": true,
          "autoincrement": false
        },
        "updated_at": {
          "name": "updated_at",
          "type": "timestamp",
          "primaryKey": false,
          "notNull": true,
          "autoincrement": false,
          "default": "(now())"
        }
      },
      "indexes": {},
      "foreignKeys": {},
      "compositePrimaryKeys": {
        "seed_sync_state_scope": {
          "name": "seed_sync_state_scope",
          "columns": ["scope"]
        }
      },
      "uniqueConstraints": {},
      "checkConstraint": {}
    }
  },
  "views": {},
  "_meta": {
    "schemas": {},
    "tables": {},
    "columns": {}
  },
  "internal": {
    "tables": {},
    "indexes": {}
  }
}
